codeflexDian/SOAPSing.py
codeflexDian/Signing.py
codeflexDian/SingExceptions.py
codeflexDian/SingNS.py
codeflexDian/Utils.py
codeflexDian/__init__.py
codeflexDian-1.3.0.dist-info/LICENSE
codeflexDian-1.3.0.dist-info/METADATA
codeflexDian-1.3.0.dist-info/WHEEL
codeflexDian-1.3.0.dist-info/top_level.txt
codeflexDian-1.3.0.dist-info/RECORD
