Metadata-Version: 2.1
Name: codeflexDian
Version: 1.3.0
Summary: ¡Firma tus peticiones a la DIAN: rangos de numeración o facturas con CodeFlex!
Home-page: https://codeflex.com.co/
Author: CODEFLEX CLOUD S.A.S.
Author-email: info@codeflex.com.co
License: This software is owned by CodeFlex S.A.S. and is protected by applicable copyright laws. The distribution and use of this software are subject to the terms and conditions outlined below.
Project-URL: Bug Tracker, https://docs.codeflex.com.co/
Classifier: Programming Language :: Python :: 3
Classifier: License :: OSI Approved :: MIT License
Classifier: Operating System :: OS Independent
Requires-Python: >=3.6
License-File: LICENSE
Requires-Dist: boto3
Requires-Dist: cryptography
Requires-Dist: lxml
Requires-Dist: pytz
Requires-Dist: defusedxml
